warriorgnmi/__init__.py
warriorgnmi/Actions/__init__.py
warriorgnmi/Actions/GnmiActions/__init__.py
warriorgnmi/Actions/GnmiActions/gnmi_actions.py
warriorgnmi/ClassUtils/__init__.py
warriorgnmi/ClassUtils/gnmi_utils_class.py
warriorgnmi/ClassUtils/ssh_utils_class.py
warriorgnmi/ClassUtils/WNetwork/__init__.py
warriorgnmi/ClassUtils/WNetwork/base_class.py
warriorgnmi/ClassUtils/WNetwork/connection.py
warriorgnmi/ClassUtils/WNetwork/diagnostics.py
warriorgnmi/ClassUtils/WNetwork/file_ops.py
warriorgnmi/ClassUtils/WNetwork/loging.py
warriorgnmi/ClassUtils/WNetwork/network_class.py
warriorgnmi/ClassUtils/WNetwork/warrior_cli_class.py
warriorgnmi/Gnmi/gnmi_cli
warriorgnmi/ProductDrivers/__init__.py
warriorgnmi/ProductDrivers/gnmi_driver.py
warriorgnmi/Utils/__init__.py
warriorgnmi/Utils/cli_Utils.py
warriorgnmi-1.0.0.dist-info/METADATA
warriorgnmi-1.0.0.dist-info/WHEEL
warriorgnmi-1.0.0.dist-info/top_level.txt
warriorgnmi-1.0.0.dist-info/RECORD
